odoo/addons/l10n_ro_journal_register/README.rst
odoo/addons/l10n_ro_journal_register/__init__.py
odoo/addons/l10n_ro_journal_register/__manifest__.py
odoo/addons/l10n_ro_journal_register/i18n/l10n_ro_journal_register.pot
odoo/addons/l10n_ro_journal_register/readme/CONTRIBUTORS.rst
odoo/addons/l10n_ro_journal_register/readme/DESCRIPTION.rst
odoo/addons/l10n_ro_journal_register/readme/INSTALL.rst
odoo/addons/l10n_ro_journal_register/report/__init__.py
odoo/addons/l10n_ro_journal_register/report/journal_register_report.py
odoo/addons/l10n_ro_journal_register/report/journal_register_report_view.xml
odoo/addons/l10n_ro_journal_register/security/ir.model.access.csv
odoo/addons/l10n_ro_journal_register/static/description/icon.png
odoo/addons/l10n_ro_journal_register/static/description/icon.svg
odoo/addons/l10n_ro_journal_register/static/description/index.html
odoo/addons/l10n_ro_journal_register/tests/__init__.py
odoo/addons/l10n_ro_journal_register/tests/test_journal_register.py
odoo14_addon_l10n_ro_journal_register-14.0.1.2.0.dist-info/METADATA
odoo14_addon_l10n_ro_journal_register-14.0.1.2.0.dist-info/WHEEL
odoo14_addon_l10n_ro_journal_register-14.0.1.2.0.dist-info/top_level.txt
odoo14_addon_l10n_ro_journal_register-14.0.1.2.0.dist-info/RECORD
